neem_query/__init__.py
neem_query/enums.py
neem_query/neem_interface.py
neem_query/neem_query.py
neem_query/neems_database.py
neem_query/query_result.py
NEEMQuery-1.1.4.dist-info/LICENSE
NEEMQuery-1.1.4.dist-info/METADATA
NEEMQuery-1.1.4.dist-info/WHEEL
NEEMQuery-1.1.4.dist-info/top_level.txt
NEEMQuery-1.1.4.dist-info/RECORD
