Metadata-Version: 2.1
Name: NEEMQuery
Version: 1.1.4
Summary: Querying the NEEMs (Narrative Enabled Episodic Memories) datasbase
Author-email: Abdelrhman Bassiouny <abassiou@uni-bremen.de>
License: GNU GENERAL PUBLIC LICENSE
Project-URL: Homepage, https://github.com/AbdelrhmanBassiouny/NEEMQuery
Keywords: query,neems,database,sql,robotics,knowledge,memories,episodic
Classifier: Programming Language :: Python :: 3
Requires-Python: >=3.8
License-File: LICENSE
Requires-Dist: pandas
Requires-Dist: sqlalchemy
Requires-Dist: typing-extensions
Requires-Dist: PyMySQL
